[{"content":"为什么这个页面无法显示呢？ ","permalink":"https://942avril.github.io/posts/learncpp/c++%E4%B8%AD%E5%A6%82%E4%BD%95%E5%A4%84%E7%90%86%E5%A4%9A%E8%BF%94%E5%9B%9E%E5%80%BC/","summary":"\u003ch2 id=\"为什么这个页面无法显示呢\"\u003e为什么这个页面无法显示呢？\u003c/h2\u003e","title":"C++中如何处理多返回值"},{"content":"\n目录 C++中如何处理多返回值\n","permalink":"https://942avril.github.io/posts/learncpp/%E7%9B%AE%E5%BD%95/","summary":"\u003cp\u003e\u003cimg loading=\"lazy\" src=\"/posts/learncpp/%E7%9B%AE%E5%BD%95/attachments/Pasted%20image%2020260102130747.png\"\u003e\u003c/p\u003e\n\u003ch2 id=\"目录\"\u003e目录\u003c/h2\u003e\n\u003cp\u003e\u003ca href=\"https://942avril.github.io/posts/learncpp/c++%E4%B8%AD%E5%A6%82%E4%BD%95%E5%A4%84%E7%90%86%E5%A4%9A%E8%BF%94%E5%9B%9E%E5%80%BC/\"\u003eC++中如何处理多返回值\u003c/a\u003e\u003c/p\u003e","title":"学习C++"}]